b3tojson/__init__.py
b3tojson/__main__.py
b3tojson/_version.py
b3tojson/cli.py
b3tojson/data.py
b3tojson/fetcher.py
b3tojson/processor.py
b3tojson-1.0.1.dist-info/LICENSE.md
b3tojson-1.0.1.dist-info/METADATA
b3tojson-1.0.1.dist-info/WHEEL
b3tojson-1.0.1.dist-info/entry_points.txt
b3tojson-1.0.1.dist-info/top_level.txt
b3tojson-1.0.1.dist-info/RECORD
