Metadata-Version: 2.1
Name: b3tojson
Version: 1.0.1
Summary: B3 to JSON format converter
Home-page: https://github.com/gerson23/b3tojson
Author: Gerson Carlos
Author-email: gerson.mtg@gmail.com
License: MIT
Platform: UNKNOWN
Classifier: Environment :: Console
Classifier: Intended Audience :: Developers
Classifier: Intended Audience :: Financial and Insurance Industry
Classifier: License :: OSI Approved :: MIT License
Classifier: Programming Language :: Python :: 3 :: Only
Classifier: Programming Language :: Python :: 3.6
Classifier: Programming Language :: Python :: 3.7
Classifier: Programming Language :: Python :: 3.8
Classifier: Topic :: Utilities
Requires-Python: >=3.6
Requires-Dist: requests (==2.23.0)
Requires-Dist: jsonpickle (==1.3)
